{
  "data": [
    {
      "type": "HOSPITAL",
      "name": "Cecilia Hospital",
      "latitude": 13.95396,
      "longitude": 121.3392,
      "photoUrl": "https://streetviewpixels-pa.googleapis.com/v1/thumbnail?panoid=kfEEVRy17B596hfTq3M2Vw&cb_client=search.gws-prod.gps&w=408&h=240&yaw=201.54822&pitch=0&thumbfov=100"
    },
    {
      "type": "HOSPITAL",
      "name": "Hospital De Soledad",
      "latitude": 13.9598,
      "longitude": "121.3238°",
      "photoUrl": "https://streetviewpixels-pa.googleapis.com/v1/thumbnail?panoid=pBLcbzZqRqInZ6-EZjfX7w&cb_client=search.gws-prod.gps&w=408&h=240&yaw=218.32236&pitch=0&thumbfov=100"
    },
    {
      "type": "HOSPITAL",
      "name": "DRL Medical Clinic",
      "latitude": 13.9588831,
      "longitude": 121.3239445,
      "photoUrl": "https://streetviewpixels-pa.googleapis.com/v1/thumbnail?panoid=DuvDisE4aU4h8nR-9mDCnA&cb_client=search.gws-prod.gps&w=408&h=240&yaw=228.91487&pitch=0&thumbfov=100"
    },
    {
      "type": "HOSPITAL",
      "name": "John Paul Clinical Laboratory",
      "latitude": 13.95851,
      "longitude": 121.32542,
      "photoUrl": "https://streetviewpixels-pa.googleapis.com/v1/thumbnail?panoid=Cb4z3tKWID9GFKLO0tOxyg&cb_client=search.gws-prod.gps&w=408&h=240&yaw=237.25143&pitch=0&thumbfov=100"
    },
    {
      "type": "HOSPITAL",
      "name": "Liwag Medical Clinic Inc.",
      "latitude": 13.948854,
      "longitude": 121.353086,
      "photoUrl": "https://streetviewpixels-pa.googleapis.com/v1/thumbnail?panoid=0ASGoOVnVMGSYcBClsBLbQ&cb_client=search.gws-prod.gps&w=408&h=240&yaw=22.35937&pitch=0&thumbfov=100"
    },
    {
      "type": "HOSPITAL",
      "name": "United Candelaria Doctors Hospital",
      "latitude": 51.17934298,
      "longitude": 89.296875,
      "photoUrl": "https://streetviewpixels-pa.googleapis.com/v1/thumbnail?panoid=ytWIdWnbdE0GD4SO1QHGdQ&cb_client=search.gws-prod.gps&w=408&h=240&yaw=180.2049&pitch=0&thumbfov=100"
    },
    {
      "type": "HOSPITAL",
      "name": "Candelaria District Hospital",
      "latitude": 13.93020188,
      "longitude": 121.4206298,
      "photoUrl": "https://streetviewpixels-pa.googleapis.com/v1/thumbnail?panoid=r5fm60Q4SRxaMF1zx6Pisw&cb_client=search.gws-prod.gps&w=408&h=240&yaw=76.206116&pitch=0&thumbfov=100"
    },
    {
      "type": "HOSPITAL",
      "name": "Peter Paul Medical Center of Candelaria Inc.",
      "latitude": 13.92631537,
      "longitude": 121.4234411,
      "photoUrl": "https://lh5.googleusercontent.com/p/AF1QipNaIEC0y3BYLG8wQAwn6OYo1eVCSz0IlTGTW2u8=w408-h306-k-no "
    },
    {
      "type": "HOSPITAL",
      "name": "Greg Hospital",
      "latitude": 13.96288838,
      "longitude": 121.5225642,
      "photoUrl": "https://streetviewpixels-pa.googleapis.com/v1/thumbnail?panoid=W9Nxna12N8ECuGwCIJ3EPQ&cb_client=search.gws-prod.gps&w=408&h=240&yaw=103.7387&pitch=0&thumbfov=100"
    },
    {
      "type": "HOSPITAL",
      "name": "Soler General Hospital",
      "latitude": 14.3405792,
      "longitude": 121.0839996,
      "photoUrl": "https://streetviewpixels-pa.googleapis.com/v1/thumbnail?panoid=Y3OJGa6fJXx8GDSuoMy1Wg&cb_client=search.gws-prod.gps&w=408&h=240&yaw=313.8459&pitch=0&thumbfov=100"
    },
    {
      "type": "HOSPITAL",
      "name": "Primary General Hospital",
      "latitude": 13.9642,
      "longitude": 121.5276,
      "photoUrl": "https://streetviewpixels-pa.googleapis.com/v1/thumbnail?panoid=49UCfBAt88uM0JtYnB9ehw&cb_client=search.gws-prod.gps&w=408&h=240&yaw=3.5129573&pitch=0&thumbfov=100"
    },
    {
      "type": "HOSPITAL",
      "name": "Tayabas Community Hospital Inc.",
      "latitude": 14.02065,
      "longitude": 121.59729,
      "photoUrl": "https://lh5.googleusercontent.com/p/AF1QipMyg0M9T4MTO1U2KBDFy9z9RzGqDf19yBDw3MTd=w408-h544-k-no"
    },
    {
      "type": "HOSPITAL",
      "name": "Mount Carmel Diocesan General Hospital",
      "latitude": 13.94080086,
      "longitude": 121.6112496,
      "photoUrl": "https://lh5.googleusercontent.com/p/AF1QipMMa1R-WBALW-sYKvuoxdAzP62sItpEKsSHPvY=w408-h261-k-no"
    },
    {
      "type": "HOSPITAL",
      "name": "Lucena United Doctors Hospital and Medical Center",
      "latitude": 13.9379,
      "longitude": 121.61339,
      "photoUrl": "https://lh5.googleusercontent.com/p/AF1QipNsDzrQeC7b1vTthZj8xd3l4ZlideQBxSkfx2r_=w408-h306-k-no"
    },
    {
      "type": "HOSPITAL",
      "name": "Camp Nakar Station Hospital",
      "latitude": 13.95544091,
      "longitude": 121.6088875,
      "photoUrl": "https://lh5.googleusercontent.com/tg8qHTHb8LeE5tx6Oi7TttcxuuHBWn6zqZcJojN4qBdAWuaacKT9EMGScUsuZb0=w426-h240-k-no"
    },
    {
      "type": "HOSPITAL",
      "name": "Quezon Memorial Hospital",
      "latitude": 13.94239081,
      "longitude": 121.6126257,
      "photoUrl": "https://lh4.googleusercontent.com/J_IqQALZaNMKjbMhY_rthIfGFKxz9AcPa0BtwJe98gJ_36bYbDNr-NTIDJW6Hko=w426-h240-k-no"
    },
    {
      "type": "HOSPITAL",
      "name": "St. Anne General Hospital Inc.",
      "latitude": 13.9439497,
      "longitude": 121.5952072,
      "photoUrl": "https://lh5.googleusercontent.com/p/AF1QipMQaMjagROOtIaobReqPEcgtIMmH4PJEBA-dqw=w408-h306-k-no"
    },
    {
      "type": "HOSPITAL",
      "name": "Alilio's Medical Clinic and Saint Cecilia Hospital",
      "latitude": 14.015496,
      "longitude": 121.401029,
      "photoUrl": "https://streetviewpixels-pa.googleapis.com/v1/thumbnail?panoid=vAQey6vJ3uxL-awR2zVVFA&cb_client=search.gws-prod.gps&w=408&h=240&yaw=133.55753&pitch=0&thumbfov=100"
    }
  ]
}
